pysoleng/__init__.py
pysoleng/models.py
pysoleng/solar.py
pysoleng/timeplace.py
pysoleng/utils.py
pysoleng-0.0.1.dist-info/LICENSE
pysoleng-0.0.1.dist-info/METADATA
pysoleng-0.0.1.dist-info/WHEEL
pysoleng-0.0.1.dist-info/top_level.txt
pysoleng-0.0.1.dist-info/RECORD
