Metadata-Version: 2.1
Name: pysoleng
Version: 0.0.1
Summary: A package to study solar energy and its applications.
Home-page: https://notabug.org/pmlpm/pysoleng
Author: Pedro L. Magalhães
Author-email: pmlpm@posteo.de
Project-URL: Bug Tracker, https://notabug.org/pmlpm/pysoleng/issues
Classifier: Programming Language :: Python :: 3
Classifier: License :: OSI Approved :: GNU General Public License v3 (GPLv3)
Classifier: Operating System :: OS Independent
Requires-Python: >=3.8
License-File: LICENSE
Requires-Dist: numpy (>=1.7)
Requires-Dist: pyproj
